storix/__init__.py
storix/__main__.py
storix/_internal/__init__.py
storix/_internal/_lazy.py
storix/aio/__init__.py
storix/aio/factory.py
storix/aio/providers/__init__.py
storix/aio/providers/_base.py
storix/aio/providers/_base_tree.py
storix/aio/providers/_proto.py
storix/aio/providers/_types.py
storix/aio/providers/azure.py
storix/aio/providers/local.py
storix/cli/__init__.py
storix/cli/app.py
storix/cli/shell.py
storix/constants.py
storix/core/__init__.py
storix/core/find.py
storix/core/tree.py
storix/core/word_count.py
storix/errors.py
storix/factory.py
storix/models.py
storix/providers/__init__.py
storix/providers/_base.py
storix/providers/_base_tree.py
storix/providers/_proto.py
storix/providers/azure.py
storix/providers/local.py
storix/py.typed
storix/sandbox.py
storix/security.py
storix/settings.py
storix/types.py
storix/utils/__init__.py
storix/utils/paths.py
storix/utils/streaming.py
storix-0.1.0.dist-info/WHEEL
storix-0.1.0.dist-info/entry_points.txt
storix-0.1.0.dist-info/METADATA
storix-0.1.0.dist-info/RECORD
