Metadata-Version: 2.3
Name: storix
Version: 0.1.0
Summary: Storage Unix Style for Developers
Keywords: storage,filesystem,azure,local,async,sandbox
Author: Mohanad Ghali
Author-email: Mohanad Ghali <mghalix@gmail.com>
License: Apache-2.0
Classifier: Development Status :: 4 - Beta
Classifier: Intended Audience :: Developers
Classifier: License :: OSI Approved :: Apache Software License
Classifier: Operating System :: OS Independent
Classifier: Programming Language :: Python :: 3
Classifier: Programming Language :: Python :: 3.10
Classifier: Programming Language :: Python :: 3.11
Classifier: Programming Language :: Python :: 3.12
Classifier: Topic :: System :: Filesystems
Classifier: Topic :: Software Development :: Libraries :: Python Modules
Requires-Dist: storix[core,local]
Requires-Dist: storix[local,azure,cli] ; extra == 'all'
Requires-Dist: azure-storage-file-datalake>=12.22.0 ; extra == 'azure'
Requires-Dist: aiohttp>=3.13.2 ; extra == 'azure'
Requires-Dist: rich>=14.2.0 ; extra == 'cli'
Requires-Dist: rich-toolkit>=0.17.0 ; extra == 'cli'
Requires-Dist: typer>=0.20.0 ; extra == 'cli'
Requires-Dist: loguru>=0.7.3 ; extra == 'core'
Requires-Dist: pydantic>=2.0.0 ; extra == 'core'
Requires-Dist: pydantic-settings>=2.0.0 ; extra == 'core'
Requires-Dist: python-magic>=0.4.27 ; extra == 'core'
Requires-Dist: wrapt>=2.0.1 ; extra == 'core'
Requires-Dist: aiofiles>=25.1.0 ; extra == 'local'
Requires-Python: >=3.12
Project-URL: Changelog, https://github.com/mghalix/storix/blob/main/release-notes.md
Project-URL: Documentation, https://github.com/mghalix/storix#readme
Project-URL: Homepage, https://github.com/mghalix/storix
Project-URL: Issues, https://github.com/mghalix/storix/issues
Project-URL: Repository, https://github.com/mghalix/storix
Provides-Extra: all
Provides-Extra: azure
Provides-Extra: cli
Provides-Extra: core
Provides-Extra: local
